4 bit sync udc/design.sv
// design: describes the behaviour of system
// behavioural modelling
module syncupdown(output reg [3:0] count, input clk, rst, status);
  initial count=0;
  always @ (posedge clk)
    begin 
      if(status==0)
        begin
         if(rst)
           count=0;
         else
           count=count+1;
        end
      else
        begin
          if(status)
            begin
              if(rst)
                count=0;
              else
                count=count-1;
            end
        end
    end
  always @ (posedge status)
    begin
      count=15;
    end
  always @ (negedge status)
    begin
      count=0;
    end
endmodule

4 bit sync udc/testbench.sv
// testbench: to check if the design codes are correct

module syncupdown_tb();
  
  reg clk, rst, status;
  wire [3:0] count;
  
  syncupdown m1(count, clk, rst, status);

 initial begin

	$dumpfile("dump.vcd");
    $dumpvars(1);

	clk=0; rst=1; status=0;
   #20 rst=0;
   #200 status=1;
   #400 status=0;
   #600 $finish;

 end
  always #10 clk=~clk;
endmodule

4 bit sync udc/dump.vcd
$date
Sat Jan  8 14:14:51 2022
$end
$version
Riviera-PRO Version 2020.04.130.7729
$end
$timescale
1 ns
$end

$scope module syncupdown_tb $end
$var wire 4 ! count [3:0] $end
$var reg 1 " clk $end
$var reg 1 # rst $end
$var reg 1 $ status $end
$upscope $end

$enddefinitions $end
$dumpvars
b0 !
0"
1#
0$
$end
#10
1"
#20
0#
0"
#30
1"
b1 !
#40
0"
#50
1"
b10 !
#60
0"
#70
1"
b11 !
#80
0"
#90
1"
b100 !
#100
0"
#110
1"
b101 !
#120
0"
#130
1"
b110 !
#140
0"
#150
1"
b111 !
#160
0"
#170
1"
b1000 !
#180
0"
#190
1"
b1001 !
#200
0"
#210
1"
b1010 !
#220
1$
0"
b1111 !
#230
1"
b1110 !
#240
0"
#250
1"
b1101 !
#260
0"
#270
1"
b1100 !
#280
0"
#290
1"
b1011 !
#300
0"
#310
1"
b1010 !
#320
0"
#330
1"
b1001 !
#340
0"
#350
1"
b1000 !
#360
0"
#370
1"
b111 !
#380
0"
#390
1"
b110 !
#400
0"
#410
1"
b101 !
#420
0"
#430
1"
b100 !
#440
0"
#450
1"
b11 !
#460
0"
#470
1"
b10 !
#480
0"
#490
1"
b1 !
#500
0"
#510
1"
b0 !
#520
0"
#530
1"
b1111 !
#540
0"
#550
1"
b1110 !
#560
0"
#570
1"
b1101 !
#580
0"
#590
1"
b1100 !
#600
0"
#610
1"
b1011 !
#620
0$
0"
b0 !
#630
1"
b1 !
#640
0"
#650
1"
b10 !
#660
0"
#670
1"
b11 !
#680
0"
#690
1"
b100 !
#700
0"
#710
1"
b101 !
#720
0"
#730
1"
b110 !
#740
0"
#750
1"
b111 !
#760
0"
#770
1"
b1000 !
#780
0"
#790
1"
b1001 !
#800
0"
#810
1"
b1010 !
#820
0"
#830
1"
b1011 !
#840
0"
#850
1"
b1100 !
#860
0"
#870
1"
b1101 !
#880
0"
#890
1"
b1110 !
#900
0"
#910
1"
b1111 !
#920
0"
#930
1"
b0 !
#940
0"
#950
1"
b1 !
#960
0"
#970
1"
b10 !
#980
0"
#990
1"
b11 !
#1000
0"
#1010
1"
b100 !
#1020
0"
#1030
1"
b101 !
#1040
0"
#1050
1"
b110 !
#1060
0"
#1070
1"
b111 !
#1080
0"
#1090
1"
b1000 !
#1100
0"
#1110
1"
b1001 !
#1120
0"
#1130
1"
b1010 !
#1140
0"
#1150
1"
b1011 !
#1160
0"
#1170
1"
b1100 !
#1180
0"
#1190
1"
b1101 !
#1200
0"
#1210
1"
b1110 !
