4 bit sync dc/design.sv
// design: describes the behaviour of system
// behavioural modelling
module syncdown(output reg [3:0] count, input clk, rst);
  always @ (posedge clk or posedge rst)
    
    begin
      
      if(rst)
        count<=0;
      else if(clk)
        count<=count-1;
      else
        count<=0;
  
    end
  
endmodule

4 bit sync dc/testbench.sv
// testbench: to check if the design codes are correct

module syncdown_tb();
  
  reg clk, rst;
  wire [3:0] count;
  
  syncdown m1(count, clk, rst);

 initial begin

	$dumpfile("dump.vcd");
    
    $dumpvars(1);

	clk=0;
    rst=1;
   #20 rst=0;
   #150 $stop;

 end
  always #5 clk=~clk;
endmodule

4 bit sync dc/dump.vcd
$date
Sat Jan  8 14:14:03 2022
$end
$version
Riviera-PRO Version 2020.04.130.7729
$end
$timescale
1 ns
$end

$scope module syncdown_tb $end
$var wire 4 ! count [3:0] $end
$var reg 1 " clk $end
$var reg 1 # rst $end
$upscope $end

$enddefinitions $end
$dumpvars
b0 !
0"
1#
$end
#5
1"
#10
0"
#15
1"
#20
0#
0"
#25
1"
b1111 !
#30
0"
#35
1"
b1110 !
#40
0"
#45
1"
b1101 !
#50
0"
#55
1"
b1100 !
#60
0"
#65
1"
b1011 !
#70
0"
#75
1"
b1010 !
#80
0"
#85
1"
b1001 !
#90
0"
#95
1"
b1000 !
#100
0"
#105
1"
b111 !
#110
0"
#115
1"
b110 !
#120
0"
#125
1"
b101 !
#130
0"
#135
1"
b100 !
#140
0"
#145
1"
b11 !
#150
0"
#155
1"
b10 !
#160
0"
#165
1"
b1 !
